Metadata-Version: 2.4
Name: sanalyse-dhpy
Version: 1.0.0
Summary: A simple, accessible python toolkit for digital humanities scholars for basic and advanced text analysis, exploration, processing, parsing
Author-email: Junaid Ali <junaid695683@gmail.com>
License:                     GNU GENERAL PUBLIC LICENSE
Classifier: Programming Language :: Python :: 3
Classifier: License :: OSI Approved :: GNU General Public License v3 (GPLv3)
Classifier: Operating System :: OS Independent
License-File: LICENSE
Requires-Dist: annotated-types==0.7.0
Requires-Dist: appnope==0.1.4
Requires-Dist: asttokens==3.0.0
Requires-Dist: blis==1.3.0
Requires-Dist: catalogue==2.0.10
Requires-Dist: certifi==2025.6.15
Requires-Dist: charset-normalizer==3.4.2
Requires-Dist: click==8.2.1
Requires-Dist: cloudpathlib==0.21.1
Requires-Dist: comm==0.2.2
Requires-Dist: confection==0.1.5
Requires-Dist: conllu==6.0.0
Requires-Dist: contourpy==1.3.2
Requires-Dist: cycler==0.12.1
Requires-Dist: cymem==2.0.11
Requires-Dist: debugpy==1.8.14
Requires-Dist: decorator==5.2.1
Requires-Dist: executing==2.2.0
Requires-Dist: filelock==3.18.0
Requires-Dist: fonttools==4.58.4
Requires-Dist: fsspec==2025.5.1
Requires-Dist: gensim==4.3.2
Requires-Dist: hf-xet==1.1.5
Requires-Dist: huggingface-hub==0.33.1
Requires-Dist: idna==3.10
Requires-Dist: ipykernel==6.29.5
Requires-Dist: ipython==9.3.0
Requires-Dist: ipython-pygments-lexers==1.1.1
Requires-Dist: ipywidgets==8.1.7
Requires-Dist: jedi==0.19.2
Requires-Dist: jinja2==3.1.6
Requires-Dist: joblib==1.5.1
Requires-Dist: jupyter-client==8.6.3
Requires-Dist: jupyter-core==5.8.1
Requires-Dist: jupyterlab-widgets==3.0.15
Requires-Dist: kiwisolver==1.4.8
Requires-Dist: langcodes==3.5.0
Requires-Dist: langdetect==1.0.9
Requires-Dist: language-data==1.3.0
Requires-Dist: lxml==5.4.0
Requires-Dist: marisa-trie==1.2.1
Requires-Dist: markdown-it-py==3.0.0
Requires-Dist: markupsafe==3.0.2
Requires-Dist: matplotlib==3.10.3
Requires-Dist: matplotlib-inline==0.1.7
Requires-Dist: mdurl==0.1.2
Requires-Dist: mpmath==1.3.0
Requires-Dist: murmurhash==1.0.13
Requires-Dist: nest-asyncio==1.6.0
Requires-Dist: networkx==3.5
Requires-Dist: nltk==3.9.1
Requires-Dist: numpy==2.3.1
Requires-Dist: packaging==25.0
Requires-Dist: pandas==2.3.0
Requires-Dist: parso==0.8.4
Requires-Dist: pexpect==4.9.0
Requires-Dist: pillow==11.2.1
Requires-Dist: platformdirs==4.3.8
Requires-Dist: preshed==3.0.10
Requires-Dist: prompt-toolkit==3.0.51
Requires-Dist: psutil==7.0.0
Requires-Dist: ptyprocess==0.7.0
Requires-Dist: pure-eval==0.2.3
Requires-Dist: pydantic==2.11.7
Requires-Dist: pydantic-core==2.33.2
Requires-Dist: pygments==2.19.2
Requires-Dist: pyparsing==3.2.3
Requires-Dist: python-dateutil==2.9.0.post0
Requires-Dist: pytz==2025.2
Requires-Dist: pyyaml==6.0.2
Requires-Dist: pyzmq==27.0.0
Requires-Dist: regex==2024.11.6
Requires-Dist: requests==2.32.4
Requires-Dist: rich==14.0.0
Requires-Dist: safetensors==0.5.3
Requires-Dist: scikit-learn==1.7.0
Requires-Dist: scipy==1.16.0
Requires-Dist: sentencepiece==0.2.0
Requires-Dist: setuptools==80.9.0
Requires-Dist: shellingham==1.5.4
Requires-Dist: six==1.17.0
Requires-Dist: smart-open==7.1.0
Requires-Dist: spacy==3.8.7
Requires-Dist: spacy-legacy==3.0.12
Requires-Dist: spacy-loggers==1.0.5
Requires-Dist: srsly==2.5.1
Requires-Dist: stack-data==0.6.3
Requires-Dist: sympy==1.14.0
Requires-Dist: thinc==8.3.6
Requires-Dist: threadpoolctl==3.6.0
Requires-Dist: tokenizers==0.21.2
Requires-Dist: torch==2.7.1
Requires-Dist: tornado==6.5.1
Requires-Dist: tqdm==4.67.1
Requires-Dist: traitlets==5.14.3
Requires-Dist: transformers==4.52.4
Requires-Dist: typer==0.16.0
Requires-Dist: typing-extensions==4.14.0
Requires-Dist: typing-inspection==0.4.1
Requires-Dist: tzdata==2025.2
Requires-Dist: urllib3==2.5.0
Requires-Dist: wasabi==1.1.3
Requires-Dist: wcwidth==0.2.13
Requires-Dist: weasel==0.4.1
Requires-Dist: whoosh==2.7.4
Requires-Dist: widgetsnbextension==4.0.14
Requires-Dist: wrapt==1.17.2
Dynamic: license-file
